MANIFEST.in
setup.py
remote_docker.egg-info/PKG-INFO
remote_docker.egg-info/SOURCES.txt
remote_docker.egg-info/dependency_links.txt
remote_docker.egg-info/entry_points.txt
remote_docker.egg-info/requires.txt
remote_docker.egg-info/top_level.txt
src/__init__.py
src/__main__.py
src/errors.py
src/parser.py
src/remotedocker.py
src/utils.py
src/actions/__init__.py
src/actions/list.py
src/actions/remove.py
src/actions/restart.py
src/actions/run.py
src/actions/ssh.py
src/actions/stop.py
src/actions/sync.py
src/actions/sync_up.py
src/actions/lib/__init__.py
src/actions/lib/docker.py
src/actions/lib/rsync.py
src/lib/__init__.py
src/lib/ptty.py
src/static/.remotedignore
test/test_arrow.py
test/test_cli.py
test/test_docker.py
test/test_lib_docker.py
test/test_lib_rsync.py
test/test_list.py
test/test_parser.py
test/test_parsing.py
test/test_proxy.py
test/test_ptty.py
test/test_rsync.py
test/test_run.py
test/test_ssh.py
test/test_test_utils.py
test/test_utils.py