Metadata-Version: 1.0
Name: remote-docker
Version: 0.19
Summary: Run your script in a docker on another machine as if it were on yours
Home-page: https://github.com/phizaz/remote-docker
Author: Konpat Preechakul
Author-email: the.akita.ta@gmail.com
License: UNKNOWN
Keywords: remote,utility
Platform: UNKNOWN
